{
    "paragraph": {
        "HTMLAttributes": {
            // "class": {
            //     "default": "table"
            // }
        },
        "tag": "p"
    },
    "table" : {
        "HTMLAttributes": {
            // "class": {
            //     "default": "table"
            // },
            // ":tablenote": {
            //     "default": "table"
            // }
        },
        "tag": "table"
    },
    "otherConfigurations":{
        "headingLevels": [1,2,3,4],
        "citation": "true",
        "tablePro": "true",             //table with note
        "tableMustContainNote": "false"  //table must contain note
    }
}